atcrawler/__init__.py
atcrawler/atcoder_session.py
atcrawler/atcrawler.py
atcrawler/environment_initializer.py
atcrawler/submission_collector.py
atcrawler/utils.py
atcrawler-0.0.1.dist-info/METADATA
atcrawler-0.0.1.dist-info/WHEEL
atcrawler-0.0.1.dist-info/entry_points.txt
atcrawler-0.0.1.dist-info/top_level.txt
atcrawler-0.0.1.dist-info/RECORD
