Metadata-Version: 2.1
Name: atcrawler
Version: 0.0.1
Summary: A crawling tool for submitted codes of AtCoder.
Author-email: void-hoge <coilgunrailgun@gmail.com>
License: GNU GPL v3
Classifier: Programming Language :: Python :: 3
Classifier: Operating System :: OS Independent
Requires-Python: >=3.11
Requires-Dist: requests ~=2.23.0
Requires-Dist: beautifulsoup4 ~=4.11.2
Provides-Extra: dev
Requires-Dist: build ; extra == 'dev'
Requires-Dist: twine ; extra == 'dev'
